MANIFEST.in
README.rst
license.txt
setup.py
maguey/__init__.py
maguey/api.py
maguey.egg-info/PKG-INFO
maguey.egg-info/SOURCES.txt
maguey.egg-info/dependency_links.txt
maguey.egg-info/not-zip-safe
maguey.egg-info/requires.txt
maguey.egg-info/top_level.txt