Metadata-Version: 1.1
Name: maguey
Version: 0.0.1
Summary: Python SDK for Agave API
Home-page: http://github.com/andrewmagill/maguey
Author: Andrew Magill
Author-email: andrew.b.magill@gmail.com
License: MIT
Keywords: agave,hpc
Platform: UNKNOWN
Classifier: Development Status :: 2 - Pre-Alpha
Classifier: License :: OSI Approved :: MIT License
Classifier: Programming Language :: Python :: 2.7
Classifier: Natural Language :: English
